browserstack/__init__.py
browserstack/bserrors.py
browserstack/local.py
browserstack/local_binary.py
browserstack_local-1.2.11.dist-info/LICENSE.txt
browserstack_local-1.2.11.dist-info/METADATA
browserstack_local-1.2.11.dist-info/WHEEL
browserstack_local-1.2.11.dist-info/top_level.txt
browserstack_local-1.2.11.dist-info/RECORD
