Metadata-Version: 2.1
Name: browserstack-local
Version: 1.2.11
Summary: Python bindings for Browserstack Local
Home-page: https://github.com/browserstack/browserstack-local-python
Download-URL: https://github.com/browserstack/browserstack-local-python/archive/master.zip
Author: BrowserStack
Author-email: support@browserstack.com
Keywords: BrowserStack,Local,selenium,testing
License-File: LICENSE.txt
Requires-Dist: psutil
